md2ankicard/__init__.py
md2ankicard/cli.py
md2ankicard/converter.py
md2ankicard-0.1.0.dist-info/LICENSE.txt
md2ankicard-0.1.0.dist-info/METADATA
md2ankicard-0.1.0.dist-info/WHEEL
md2ankicard-0.1.0.dist-info/entry_points.txt
md2ankicard-0.1.0.dist-info/RECORD
