Metadata-Version: 2.3
Name: md2ankicard
Version: 0.1.0
Summary: Convert markdown files to Anki cards
License: MIT
Keywords: anki,markdown,flashcards,converter,cli
Author: Andrew Romanenco
Author-email: andrew@romanenco.com
Requires-Python: >=3.9
Classifier: License :: OSI Approved :: MIT License
Classifier: Development Status :: 5 - Production/Stable
Classifier: Intended Audience :: End Users/Desktop
Classifier: Topic :: Education
Classifier: Topic :: Utilities
Classifier: Environment :: Console
Classifier: Programming Language :: Python :: 3
Requires-Dist: genanki (>=0.13.1,<0.14.0)
Requires-Dist: markdown (>=3.8.2,<4.0.0)
